{
  "buy_setup_count": 0,
  "orders_submitted_this_run": 0,
  "paper_only": true,
  "processed_at": "2026-07-23T18:27:01.896762+00:00",
  "results": [
    {
      "order": {
        "reason": "WAIT signals are alert-only",
        "submitted": false
      },
      "signal_key": "WAIT|2026-07-23|MARA|12.96|12.4|13.06",
      "symbol": "MARA",
      "telegram": {
        "reason": "sent",
        "sent": true
      }
    },
    {
      "order": {
        "reason": "WAIT signals are alert-only",
        "submitted": false
      },
      "signal_key": "WAIT|2026-07-23|XOM|157.44|154.17|157.91",
      "symbol": "XOM",
      "telegram": {
        "reason": "sent",
        "sent": true
      }
    },
    {
      "order": {
        "reason": "WAIT signals are alert-only",
        "submitted": false
      },
      "signal_key": "WAIT|2026-07-23|RIOT|24.14|23.15|24.29",
      "symbol": "RIOT",
      "telegram": {
        "reason": "sent",
        "sent": true
      }
    }
  ],
  "wait_alerts_attempted_this_run": 3,
  "wait_alerts_sent_this_run": 3,
  "wait_alerts_suppressed_this_run": 0,
  "wait_setup_alert_count": 3
}